bio_tree/__init__.py
bio_tree/chembal_gene.py
bio_tree-0.1.0.dist-info/METADATA
bio_tree-0.1.0.dist-info/WHEEL
bio_tree-0.1.0.dist-info/RECORD
