Metadata-Version: 2.1
Name: bio-tree
Version: 0.1.0
Summary: 
Author: younthing
Requires-Python: >=3.12,<4.0
Classifier: Programming Language :: Python :: 3
Classifier: Programming Language :: Python :: 3.12
Requires-Dist: pandas (>=2.2.2,<3.0.0)
Requires-Dist: requests (>=2.32.3,<3.0.0)
